{
  "parent": "minecraft:recipes/root",
  "rewards": {
    "recipes": [
      "decorative_blocks:dark_oak_beam"
    ]
  },
  "criteria": {
    "has_stripped_log": {
      "trigger": "minecraft:inventory_changed",
      "conditions": {
        "items": [
          {
            "item": "minecraft:stripped_dark_oak_log"
          }
        ]
      }
    },
    "has_the_recipe": {
      "trigger": "minecraft:recipe_unlocked",
      "conditions": {
        "recipe": "decorative_blocks:dark_oak_beam"
      }
    }
  },
  "requirements": [
    [
      "has_stripped_log",
      "has_the_recipe"
    ]
  ]
}